clusterman/__init__.py
clusterman/__main__.py
clusterman/cli/__init__.py
clusterman/cli/app.py
clusterman/cli/cli.py
clusterman/main/__init__.py
clusterman/main/ampq.py
clusterman/main/controller.py
clusterman/main/mainline.py
clusterman/main/orm.py
clusterman/main/processing.py
clusterman/main/runner.py
clusterfiles-0.1.5.dist-info/LICENSE
clusterfiles-0.1.5.dist-info/METADATA
clusterfiles-0.1.5.dist-info/WHEEL
clusterfiles-0.1.5.dist-info/top_level.txt
clusterfiles-0.1.5.dist-info/RECORD
