Metadata-Version: 2.1
Name: clusterfiles
Version: 0.1.5
Summary: Cluster file management for Python
Home-page: https://github.com/dfo-meds/clusterman
Author: Erin Turnbull
Author-email: erin.a.turnbull@gmail.com
Project-URL: Bug Tracker, https://github.com/dfo-meds/clusterman/issues
Classifier: Programming Language :: Python :: 3
Classifier: License :: OSI Approved :: MIT License
Classifier: Operating System :: OS Independent
Requires-Python: >=3.7
License-File: LICENSE
Requires-Dist: zirconium
Requires-Dist: autoinject
Requires-Dist: universalio (>=0.0.13)
Requires-Dist: pika
Requires-Dist: flask
Requires-Dist: flask-sqlalchemy
Requires-Dist: itsdangerous
Requires-Dist: toml
Requires-Dist: zrlog
